flm_htmlplus/__init__.py
flm_htmlplus/_fragmentrenderer.py
flm_htmlplus/_selenium_driver.py
flm_htmlplus/_workflow.py
flm_htmlplus/runmathjax_browser_dist.js
flm_htmlplus/runmathjax_script_dist.js
flm_htmlplus-0.1.4.dist-info/METADATA
flm_htmlplus-0.1.4.dist-info/WHEEL
flm_htmlplus-0.1.4.dist-info/RECORD
